oger/__init__.py
oger/__main__.py
oger/ctrl/__init__.py
oger/ctrl/__main__.py
oger/ctrl/parameters.py
oger/ctrl/router.py
oger/ctrl/run.py
oger/doc/__init__.py
oger/doc/becalm.py
oger/doc/bioc.py
oger/doc/brat.py
oger/doc/conll.py
oger/doc/document.py
oger/doc/europepmc.py
oger/doc/export.py
oger/doc/load.py
oger/doc/odin.py
oger/doc/pubanno.py
oger/doc/pubmed.py
oger/doc/pubtator.py
oger/doc/tsv.py
oger/doc/txt.py
oger/doc/xml.py
oger/er/__init__.py
oger/er/entity_recognition.py
oger/er/term_normalization.py
oger/eval/__init__.py
oger/eval/__main__.py
oger/eval/term_coverage.py
oger/nlp/__init__.py
oger/nlp/tokenize.py
oger/post/__init__.py
oger/post/badFP.py
oger/post/submatches.py
oger/server/__init__.py
oger/server/__main__.py
oger/server/client.py
oger/server/expfmts.py
oger/server/restfulserver.py
oger/server/static/form.html
oger/test/__init__.py
oger/test/__main__.py
oger/test/tester.py
oger/test/testfiles/test_terms.tsv
oger/test/testfiles/bioc_json/collection.json
oger/test/testfiles/bioc_json/everything-sentence.json
oger/test/testfiles/bioc_json/everything.json
oger/test/testfiles/bioc_xml/10952997.xml
oger/test/testfiles/bioc_xml/14557244.xml
oger/test/testfiles/bioc_xml/18617507.xml
oger/test/testfiles/bioc_xml/19127978.xml
oger/test/testfiles/bioc_xml/21980305.xml
oger/test/testfiles/bioc_xml/9722616.xml
oger/test/testfiles/conll/PMC6930xxx.conll
oger/test/testfiles/idfiles/bad_pmcids.txt
oger/test/testfiles/idfiles/fictious_pmcids.txt
oger/test/testfiles/idfiles/good_pmcids.txt
oger/test/testfiles/idfiles/pubmed_pmids.txt
oger/test/testfiles/idfiles/pxml_pmids.txt
oger/test/testfiles/idfiles/pxml_pmids_dl.txt
oger/test/testfiles/idfiles/random_pmcids.txt
oger/test/testfiles/idfiles/txt_ids.txt
oger/test/testfiles/pubtator/BC5CDR-example.txt
oger/test/testfiles/pubtator/NCBIdevelopset_corpus.txt
oger/test/testfiles/pubtator/tutorial-example.txt
oger/test/testfiles/pubtator_fbk/10381787.txt
oger/test/testfiles/pxml/3010203.pxml
OGER-1.5.dist-info/LICENSE
OGER-1.5.dist-info/METADATA
OGER-1.5.dist-info/WHEEL
OGER-1.5.dist-info/entry_points.txt
OGER-1.5.dist-info/top_level.txt
OGER-1.5.dist-info/RECORD
