Metadata-Version: 2.1
Name: OGER
Version: 1.5
Summary: OntoGene's Biomedical Entity Recogniser
Author: Lenz Furrer
Author-email: furrer@cl.uzh.ch
License: UNKNOWN
Platform: UNKNOWN
License-File: LICENSE
Requires-Dist: bottle
Requires-Dist: lxml
Requires-Dist: nltk
